plan_rect/__init__.py
plan_rect/camera.py
plan_rect/cli.py
plan_rect/param_io.py
plan_rect/rectify.py
plan_rect/version.py
plan_rect-0.2.0.dist-info/licenses/LICENSE
plan_rect-0.2.0.dist-info/METADATA
plan_rect-0.2.0.dist-info/WHEEL
plan_rect-0.2.0.dist-info/entry_points.txt
plan_rect-0.2.0.dist-info/top_level.txt
plan_rect-0.2.0.dist-info/RECORD
