Metadata-Version: 2.4
Name: plan-rect
Version: 0.2.0
Summary: Rectify oblique images to a plane
Author-email: Leftfield Geospatial <info@leftfield.online>
License: AGPL-3.0-or-later
Project-URL: Homepage, https://github.com/leftfield-geospatial/plan-rect
Project-URL: Source, https://github.com/leftfield-geospatial/plan-rect
Keywords: planar,orthorectification
Classifier: Programming Language :: Python :: 3
Classifier: License :: OSI Approved :: GNU Affero General Public License v3 or later (AGPLv3+)
Classifier: Operating System :: OS Independent
Requires-Python: >=3.9
License-File: LICENSE
Requires-Dist: orthority>=0.6.0
Provides-Extra: tests
Requires-Dist: pytest; extra == "tests"
Dynamic: license-file
